{
  "projectId": "gen-lang-client-0911199406",
  "appId": "1:885365632398:web:f6ef16173203e03a0b88df",
  "apiKey": "AIzaSyBj_cFpbyQ5gMSrP0ZxN3Yj-KXQT6g-US8",
  "authDomain": "gen-lang-client-0911199406.firebaseapp.com",
  "firestoreDatabaseId": "ai-studio-familystream-efcd1430-c719-415b-b009-892259ad4bd4",
  "storageBucket": "gen-lang-client-0911199406.firebasestorage.app",
  "messagingSenderId": "885365632398",
  "measurementId": "G-839PYJ90K1",
  "oAuthClientId": "885365632398-mobd26ktpg2d1vmf3jmgturl225dovv6.apps.googleusercontent.com",
  "recaptchaSiteKey": ""
}